langtorch/_VariableFunctions.py
langtorch/__init__.py
langtorch/autograd.py
langtorch/decorators.py
langtorch/main.py
langtorch/main2.py
langtorch/semalg_utils.py
langtorch/semantic_algebra.py
langtorch/session.py
langtorch/torch_utils.py
langtorch/types.py
langtorch/utils.py
langtorch/api/TODO_anthropic.py
langtorch/api/TODO_anthropic_parallel_processor.py
langtorch/api/TODO_assistant.py
langtorch/api/TODO_gcp.py
langtorch/api/TODO_gcp_parallel_processor.py
langtorch/api/__init__.py
langtorch/api/api_threading.py
langtorch/api/call.py
langtorch/api/groq.py
langtorch/api/openai.py
langtorch/api/openai_parallel_processor.py
langtorch/api/parallel_processor_utils.py
langtorch/api/tools.py
langtorch/api/utils.py
langtorch/autograd/__init__.py
langtorch/autograd/autograd.py
langtorch/autograd/backward_activation.py
langtorch/autograd/backward_prompts.py
langtorch/conf/__init__.py
langtorch/conf/defaults.yaml
langtorch/conf/new_session_template.yaml
langtorch/conf/overrides.yaml
langtorch/grammars/__init__.py
langtorch/grammars/formatters.py
langtorch/grammars/langtorch_default_parser.py
langtorch/grammars/pandoc.py
langtorch/grammars/parsers.py
langtorch/grammars/text_content_ast.py
langtorch/grammars/utils.py
langtorch/grammars/xml_parser.py
langtorch/methods/__init__.py
langtorch/methods/chain_of_density.py
langtorch/methods/chain_of_thought.py
langtorch/methods/embeddings.py
langtorch/methods/prompts.yaml
langtorch/methods/simple_prompting_methods.py
langtorch/optim/__init__.py
langtorch/optim/optimizer.py
langtorch/optim/optimizer_prompts.py
langtorch/tensors/__init__.py
langtorch/tensors/chattensor.py
langtorch/tensors/codetensor.py
langtorch/tensors/langtorchtensor.py
langtorch/tensors/losstensor.py
langtorch/tensors/markdowntensor.py
langtorch/tensors/texttensor.py
langtorch/texts/__init__.py
langtorch/texts/chat.py
langtorch/texts/code.py
langtorch/texts/markdown.py
langtorch/texts/markup.py
langtorch/texts/string.py
langtorch/texts/text.py
LangTorch-1.0.9.dist-info/METADATA
LangTorch-1.0.9.dist-info/WHEEL
LangTorch-1.0.9.dist-info/top_level.txt
LangTorch-1.0.9.dist-info/RECORD
