Metadata-Version: 2.1
Name: LangTorch
Version: 1.0.9
Summary: Framework for intuitive LLM application development with tensors.
Home-page: https://github.com/AdamSobieszek/LangTorch
Author: Adam Sobieszek
Author-email: contact@langtorch.org
Keywords: LangTorch,PyTorch,LLM,Language Models,Chat,Chains
Classifier: Programming Language :: Python :: 3
Classifier: Programming Language :: Python :: 3.8
Classifier: License :: OSI Approved :: MIT License
Classifier: Operating System :: OS Independent
Classifier: Intended Audience :: Developers
Classifier: Topic :: Software Development :: Libraries :: Python Modules
Requires-Python: >=3.8
Requires-Dist: numpy <2.0.0
Requires-Dist: torch >=2.1.0
Requires-Dist: aiohttp
Requires-Dist: nest-asyncio
Requires-Dist: openai >=1.2.4
Requires-Dist: tiktoken
Requires-Dist: pandas
Requires-Dist: retry
Requires-Dist: pyparsing
Requires-Dist: pypandoc
Requires-Dist: transformers
Requires-Dist: omegaconf
Requires-Dist: hydra-core
